MANIFEST.in
README.rst
setup.py
gtest/__init__.py
gtest/exceptions.py
gtest/gtest.py
gtest.egg-info/PKG-INFO
gtest.egg-info/SOURCES.txt
gtest.egg-info/dependency_links.txt
gtest.egg-info/entry_points.txt
gtest.egg-info/requires.txt
gtest.egg-info/top_level.txt
gtest/keyword_/Random.py
gtest/keyword_/__init__.py
gtest/keyword_/common.py
gtest/keyword_/keyword_.py
gtest/keyword_/selenium_.py
gtest/model/__init__.py
gtest/model/cases.py
gtest/model/groups.py
gtest/model/options.py
gtest/model/suite_file_tree.py
gtest/model/suite_tree.py
gtest/model/matcher/__init__.py
gtest/model/matcher/matcher.py
gtest/model/matcher/var_matcher.py
gtest/runner/__init__.py
gtest/runner/base_runner.py
gtest/runner/debug_runner.py
gtest/runner/default_runner.py
gtest/utils/__init__.py
gtest/utils/common.py
gtest/utils/console.py
gtest/utils/create_template.py
gtest/utils/data_structure.py
gtest/utils/file.py
gtest/utils/logger.py
gtest/utils/opt_parser.py
gtest/utils/output.py