Metadata-Version: 1.2
Name: gtest
Version: 0.1.3
Summary: A Automatic Test FrameWork
Home-page: https://gitee.com/CMTY/gtiee_-test
Author: NiKoChen
Author-email: NiKoChen2649@gmail.com
License: MIT
Platform: UNKNOWN
Requires-Python: >=3
